senweaver_sms/__init__.py
senweaver_sms/builder.py
senweaver_sms/config.py
senweaver_sms/message.py
senweaver_sms/phone_number.py
senweaver_sms/request.py
senweaver_sms/response.py
senweaver_sms/senweaver_sms.py
senweaver_sms/contract/__init__.py
senweaver_sms/contract/message.py
senweaver_sms/contract/strategy.py
senweaver_sms/exception/__init__.py
senweaver_sms/exception/exception.py
senweaver_sms/gateway/__init__.py
senweaver_sms/gateway/aliyun.py
senweaver_sms/gateway/baidu.py
senweaver_sms/gateway/base.py
senweaver_sms/gateway/ctyun.py
senweaver_sms/gateway/huawei.py
senweaver_sms/gateway/huyi.py
senweaver_sms/gateway/juhe.py
senweaver_sms/gateway/mas.py
senweaver_sms/gateway/qcloud.py
senweaver_sms/gateway/qiniu.py
senweaver_sms/gateway/smsbao.py
senweaver_sms/gateway/ucloud.py
senweaver_sms/gateway/yunpian.py
senweaver_sms/strategy/__init__.py
senweaver_sms/strategy/base.py
senweaver_sms/strategy/order.py
senweaver_sms/strategy/random.py
tests/__init__.py
tests/test_message.py
senweaver_sms-0.1.3.dist-info/LICENSE
senweaver_sms-0.1.3.dist-info/METADATA
senweaver_sms-0.1.3.dist-info/WHEEL
senweaver_sms-0.1.3.dist-info/top_level.txt
senweaver_sms-0.1.3.dist-info/RECORD
