Metadata-Version: 2.1
Name: senweaver-sms
Version: 0.1.3
Summary: 您的一站式 Python 短信发送解决方案
Home-page: https://github.com/senweaver/senweaver-sms
Author: senweaver
Project-URL: Bug Reports, https://github.com/senweaver/senweaver-sms/issues
Project-URL: Source, https://github.com/senweaver/senweaver-sms
Keywords: sms,message,yunpian,aliyun,qcloud,tencent,senweaver
Classifier: Development Status :: 4 - Beta
Classifier: Intended Audience :: Developers
Classifier: License :: OSI Approved :: MIT License
Classifier: Programming Language :: Python :: 3
Classifier: Programming Language :: Python :: 3.8
Classifier: Programming Language :: Python :: 3.9
Classifier: Programming Language :: Python :: 3.10
Requires-Python: >=3.8
License-File: LICENSE
Requires-Dist: requests >=2.20.0
